metaseg/__init__.py
metaseg/falai_predictor.py
metaseg/generator/__init__.py
metaseg/generator/automatic_mask_generator.py
metaseg/generator/build_sam.py
metaseg/generator/predictor.py
metaseg/modeling/__init__.py
metaseg/modeling/common.py
metaseg/modeling/image_encoder.py
metaseg/modeling/mask_decoder.py
metaseg/modeling/prompt_encoder.py
metaseg/modeling/sam.py
metaseg/modeling/transformer.py
metaseg/sahi_predictor.py
metaseg/sam_predictor.py
metaseg/utils/__init__.py
metaseg/utils/amg.py
metaseg/utils/data_utils.py
metaseg/utils/model_file_downloader.py
metaseg/utils/onnx.py
metaseg/utils/transforms.py
metaseg/webapp/__init__.py
metaseg/webapp/app.py
metaseg/webapp/demo.py
metaseg-0.7.8.dist-info/LICENSE
metaseg-0.7.8.dist-info/METADATA
metaseg-0.7.8.dist-info/WHEEL
metaseg-0.7.8.dist-info/RECORD
