Metadata-Version: 2.1
Name: metaseg
Version: 0.7.8
Summary: MetaSeg: Packaged version of the Segment Anything repository
Home-page: https://github.com/kadirnar/segment-anything-video
License: Apache-2.0
Keywords: pytorch,segment-anything-video,metaseg
Author: Kadir Nar
Author-email: kadir.nar@hotmail.com
Maintainer: Kadir Nar
Maintainer-email: kadir.nar@hotmail.com
Requires-Python: >=3.8.1,<3.12.0
Classifier: Development Status :: 5 - Production/Stable
Classifier: Intended Audience :: Developers
Classifier: Intended Audience :: Education
Classifier: Intended Audience :: Science/Research
Classifier: License :: OSI Approved :: Apache Software License
Classifier: Natural Language :: English
Classifier: Operating System :: OS Independent
Classifier: Programming Language :: Python
Classifier: Programming Language :: Python :: 3
Classifier: Programming Language :: Python :: 3.9
Classifier: Programming Language :: Python :: 3.10
Classifier: Programming Language :: Python :: 3.11
Classifier: Programming Language :: Python :: 3 :: Only
Classifier: Programming Language :: Python :: 3.8
Classifier: Topic :: Scientific/Engineering
Classifier: Topic :: Scientific/Engineering :: Artificial Intelligence
Classifier: Topic :: Scientific/Engineering :: Image Processing
Classifier: Topic :: Scientific/Engineering :: Image Recognition
Classifier: Topic :: Scientific/Engineering :: Mathematics
Classifier: Topic :: Software Development
Classifier: Topic :: Software Development :: Libraries
Classifier: Topic :: Software Development :: Libraries :: Application Frameworks
Classifier: Topic :: Software Development :: Libraries :: Python Modules
Provides-Extra: full
Provides-Extra: yolov5
Provides-Extra: yolov8
Requires-Dist: fal-serverless (>=0.6.35,<0.7.0)
Requires-Dist: matplotlib (>=3.7.1,<4.0.0)
Requires-Dist: onnx (>=1.14.0,<2.0.0) ; extra == "full"
Requires-Dist: onnxruntime (>=1.15.1,<2.0.0) ; extra == "full"
Requires-Dist: opencv-python (>=4.7.0.72,<5.0.0.0)
Requires-Dist: pillow (>=9.5.0,<10.0.0)
Requires-Dist: pycocotools (>=2.0.6,<3.0.0)
Requires-Dist: requests (>=2.31.0,<3.0.0)
Requires-Dist: sahi (>=0.11.14,<0.12.0)
Requires-Dist: torch (>=2.0.1,<3.0.0)
Requires-Dist: torchvision (>=0.15.2,<0.16.0)
Requires-Dist: tqdm (>=4.65.0,<5.0.0)
Requires-Dist: ultralytics (>=8.0.123,<9.0.0) ; extra == "full" or extra == "yolov8"
Requires-Dist: yolov5 (>=7.0.12,<8.0.0) ; extra == "full" or extra == "yolov5"
Project-URL: Documentation, https://github.com/kadirnar/segment-anything-video/blob/main/README.md
Project-URL: Repository, https://github.com/kadirnar/segment-anything-video
